pylrfd/__init__.py
pylrfd/pylrfd.py
pylrfd/eurocodes/NL.py
pylrfd/eurocodes/__init__.py
pylrfd-0.0.4.dist-info/LICENSE
pylrfd-0.0.4.dist-info/METADATA
pylrfd-0.0.4.dist-info/WHEEL
pylrfd-0.0.4.dist-info/top_level.txt
pylrfd-0.0.4.dist-info/RECORD
