Metadata-Version: 2.1
Name: pylrfd
Version: 0.0.4
Summary: A package for defining LRFD (Load and resistance factor design) base design codes
Author-email: Ronald Grefhorst <ronald@rgde.be>
Project-URL: Homepage, https://github.com/Grefron/pylrfd
Project-URL: Issues, https://github.com/Grefron/pylrfd/issues
Classifier: Programming Language :: Python :: 3
Classifier: License :: OSI Approved :: MIT License
Classifier: Operating System :: OS Independent
Requires-Python: >=3.8
License-File: LICENSE
